chemical_composition/__init__.py
chemical_composition/chemical_composition.py
chemical_composition/chemical_composition_kb.py
chemical_composition/version.txt
chemical_composition-1.0.6.dist-info/LICENSE
chemical_composition-1.0.6.dist-info/METADATA
chemical_composition-1.0.6.dist-info/WHEEL
chemical_composition-1.0.6.dist-info/top_level.txt
chemical_composition-1.0.6.dist-info/RECORD
