Metadata-Version: 2.1
Name: chemical-composition
Version: 1.0.6
Summary: chemical_composition
Home-page: https://github.com/computational-ms/chemical-composition
Author: Christian Fufezan, Manuel Köster, Johannes Leufken, Stefan Schulze
Author-email: ursgal.team@gmail.com
License: MIT
Platform: Any that supports python 3.7
Classifier: Development Status :: 4 - Beta
Classifier: Environment :: Console
Classifier: Intended Audience :: Science/Research
Classifier: Intended Audience :: Developers
Classifier: Operating System :: MacOS :: MacOS X
Classifier: Operating System :: Microsoft :: Windows
Classifier: Operating System :: POSIX
Classifier: Operating System :: POSIX :: SunOS/Solaris
Classifier: Operating System :: Unix
Classifier: Programming Language :: Python :: 3
Classifier: Programming Language :: Python :: 3.7
Classifier: Topic :: Scientific/Engineering :: Bio-Informatics
Classifier: Topic :: Scientific/Engineering :: Chemistry
Classifier: Topic :: Scientific/Engineering :: Medical Science Apps.
Classifier: Topic :: Software Development :: Libraries :: Python Modules
Requires-Python: >=3.6.0
License-File: LICENSE
Requires-Dist: nose
Requires-Dist: unimod-mapper (>=0.6.2)
